idem_salt/__init__.py
idem_salt/run.py
idem_salt/_modules/idem.py
idem_salt/_states/idem.py
idem_salt-1.3.dist-info/METADATA
idem_salt-1.3.dist-info/WHEEL
idem_salt-1.3.dist-info/entry_points.txt
idem_salt-1.3.dist-info/top_level.txt
idem_salt-1.3.dist-info/RECORD
