Metadata-Version: 2.1
Name: idem-salt
Version: 1.3
Summary: Run idem exec and state modules from salt
Home-page: https://gitlab.com/Akm0d/idem-salt
Author: Tyler Johnson
Author-email: tjohnson@saltstack.com
License: UNKNOWN
Platform: UNKNOWN
Classifier: Operating System :: OS Independent
Classifier: Programming Language :: Python
Classifier: Programming Language :: Python :: 3.6
Classifier: Programming Language :: Python :: 3.7
Classifier: Programming Language :: Python :: 3.8
Classifier: Development Status :: 5 - Production/Stable
Requires-Python: >=3.6
Requires-Dist: pop (>=13)
Requires-Dist: idem (>=7.3)
